sgx/__init__.py
sgx/constants.py
sgx/generate.sh
sgx/http.py
sgx/sgx.py
sgx/sgx_rpc_handler.py
sgx/utils.py
sgx.py-0.6.dist-info/LICENSE
sgx.py-0.6.dist-info/METADATA
sgx.py-0.6.dist-info/WHEEL
sgx.py-0.6.dist-info/top_level.txt
sgx.py-0.6.dist-info/RECORD
