Metadata-Version: 2.1
Name: sgx.py
Version: 0.6
Summary: SGX
Home-page: http://github.com/skalenetwork/sgx.py
Author: SKALE Labs
Author-email: support@skalelabs.com
License: UNKNOWN
Platform: UNKNOWN
Requires-Python: >=3.6,<4
Requires-Dist: web3 (==5.8.0)
Provides-Extra: dev
Requires-Dist: flake8 (==3.7.9) ; extra == 'dev'
Requires-Dist: coincurve (==13.0.0) ; extra == 'dev'
Requires-Dist: python-dotenv (==0.13.0) ; extra == 'dev'
Requires-Dist: twine (==3.1.1) ; extra == 'dev'
Requires-Dist: pytest (==5.4.2) ; extra == 'dev'
Requires-Dist: mock (==4.0.2) ; extra == 'dev'
Provides-Extra: linter
Requires-Dist: flake8 (==3.7.9) ; extra == 'linter'
